IronTranslator/GoogleTranslate.py
IronTranslator/__init__.py
IronTranslator/constants.py
IronTranslator-1.0.5.dist-info/LICENSE
IronTranslator-1.0.5.dist-info/METADATA
IronTranslator-1.0.5.dist-info/WHEEL
IronTranslator-1.0.5.dist-info/top_level.txt
IronTranslator-1.0.5.dist-info/RECORD
