Metadata-Version: 2.1
Name: IronTranslator
Version: 1.0.5
Summary: Google traduction
Home-page: https://github.com/med933/IronTranslator
Author: Abdelmoula
Author-email: abdelmoula.m93@gmail.com
License: MIT
Keywords: python,Google traduction,traduction,nlp,Google,translate
Platform: UNKNOWN
Classifier: Development Status :: 5 - Production/Stable
Classifier: Intended Audience :: Education
Classifier: Intended Audience :: End Users/Desktop
Classifier: License :: Freeware
Classifier: Operating System :: POSIX
Classifier: Operating System :: Microsoft :: Windows
Classifier: Operating System :: MacOS :: MacOS X
Classifier: Topic :: Education
Classifier: Programming Language :: Python
Classifier: Programming Language :: Python :: 3.6
Classifier: Programming Language :: Python :: 3.7
Classifier: Programming Language :: Python :: 3.8
Requires-Dist: selenium
Requires-Dist: tqdm
